tta_wrapper/__init__.py
tta_wrapper/__version__.py
tta_wrapper/augmentation.py
tta_wrapper/functional.py
tta_wrapper/layers.py
tta_wrapper/wrappers.py
tta_wrapper-0.0.1.dist-info/DESCRIPTION.rst
tta_wrapper-0.0.1.dist-info/METADATA
tta_wrapper-0.0.1.dist-info/RECORD
tta_wrapper-0.0.1.dist-info/WHEEL
tta_wrapper-0.0.1.dist-info/metadata.json
tta_wrapper-0.0.1.dist-info/top_level.txt
