Metadata-Version: 2.0
Name: tta-wrapper
Version: 0.0.1
Summary: Test time image augmentation for Keras models.
Home-page: UNKNOWN
Author: Pavel Yakubovskiy
Author-email: qubvel@gmail.com
License: MIT
Platform: UNKNOWN
Classifier: License :: OSI Approved :: MIT License
Classifier: Programming Language :: Python
Classifier: Programming Language :: Python :: 3
Classifier: Programming Language :: Python :: 3.6
Classifier: Programming Language :: Python :: Implementation :: CPython
Classifier: Programming Language :: Python :: Implementation :: PyPy
Requires-Python: >=3.5.0
